MANIFEST.in
README.md
setup.py
middleware/__init__.py
middleware/commandline_scripts.py
middleware/config.py
middleware/make_report.py
middleware/model.py
middleware/mysqlmodel.py
middleware/start_sync.py
middleware/utils.py
middleware/components/__init__.py
middleware/components/merging.py
middleware/components/service.py
middleware/components/synchronization.py
middleware/components/transformation.py
middleware/components/updating.py
middleware/components/user_sync_processor.py
middleware/components/providers/__init__.py
middleware/components/providers/base.py
middleware/components/providers/providers_list.py
middleware/config/example.conf
middleware/db/db_scheme.sql
middleware_test.egg-info/PKG-INFO
middleware_test.egg-info/SOURCES.txt
middleware_test.egg-info/dependency_links.txt
middleware_test.egg-info/entry_points.txt
middleware_test.egg-info/not-zip-safe
middleware_test.egg-info/requires.txt
middleware_test.egg-info/top_level.txt