Metadata-Version: 1.1
Name: middleware-test
Version: 1.2.1
Summary: Module to sync users' profiles
Home-page: UNKNOWN
Author: UNKNOWN
Author-email: probachai.yu@gmail.com
License: BSD
Platform: UNKNOWN
Classifier: Development Status :: 3 - Alpha
Classifier: Environment :: Web Environment
Classifier: Intended Audience :: Developers
Classifier: License :: OSI Approved :: BSD License
Classifier: Operating System :: OS Independent
Classifier: Programming Language :: Python :: 2
